circleutils/__init__.py
circleutils/beatmap.py
circleutils/beatmap_models.py
circleutils/collection.py
circleutils/hitobject.py
circleutils/hitobject_models.py
circleutils/logger.py
circleutils/replay.py
circleutils/types.py
circleutils/utils.py
circleutils-2023.8.5.dist-info/METADATA
circleutils-2023.8.5.dist-info/WHEEL
circleutils-2023.8.5.dist-info/top_level.txt
circleutils-2023.8.5.dist-info/RECORD
